muffin_motor.py
muffin_motor-0.3.0.dist-info/DESCRIPTION.rst
muffin_motor-0.3.0.dist-info/METADATA
muffin_motor-0.3.0.dist-info/RECORD
muffin_motor-0.3.0.dist-info/WHEEL
muffin_motor-0.3.0.dist-info/metadata.json
muffin_motor-0.3.0.dist-info/top_level.txt
