Metadata-Version: 2.0
Name: muffin-motor
Version: 0.3.0
Summary: UNKNOWN
Home-page: https://github.com/drgarcia1986/muffin-motor
Author: Diego Garcia
Author-email: drgarcia1986@gmail.com
License: MIT
Keywords: asyncio,mongo,muffin,motor
Platform: Any
Classifier: Intended Audience :: Developers
Classifier: License :: OSI Approved :: MIT License
Classifier: Natural Language :: English
Classifier: Natural Language :: Russian
Classifier: Operating System :: OS Independent
Classifier: Programming Language :: Python :: 3
Classifier: Programming Language :: Python
Classifier: Topic :: Software Development :: Libraries :: Python Modules
Classifier: Topic :: Utilities
Requires-Dist: motor (>=1.0)
Requires-Dist: muffin (>=0.5.5)
